oespy/__init__.py
oespy-0.1.dist-info/METADATA
oespy-0.1.dist-info/WHEEL
oespy-0.1.dist-info/top_level.txt
oespy-0.1.dist-info/RECORD
